{
    "fluentMethods": true,
    "relationships": [
        {
            "relationshipType": "one-to-one",
            "relationshipName": "ownerType",
            "otherEntityName": "ownerType",
            "otherEntityField": "name",
            "ownerSide": true,
            "otherEntityRelationshipName": "ownerRelation"
        },
        {
            "relationshipType": "one-to-one",
            "relationshipName": "owner",
            "otherEntityName": "userAnnex",
            "otherEntityField": "name",
            "ownerSide": true,
            "otherEntityRelationshipName": "ownerRelation"
        },
        {
            "relationshipType": "one-to-one",
            "relationshipName": "mercury",
            "otherEntityName": "mercury",
            "otherEntityField": "name",
            "ownerSide": true,
            "otherEntityRelationshipName": "ownerRelation"
        }
    ],
    "fields": [],
    "changelogDate": "20180405065747",
    "entityTableName": "owner_relation",
    "dto": "mapstruct",
    "pagination": "no",
    "service": "serviceClass",
    "jpaMetamodelFiltering": false,
    "microserviceName": "user"
}